greet_1/greet.py
greet_1-0.1.0.dist-info/METADATA
greet_1-0.1.0.dist-info/WHEEL
greet_1-0.1.0.dist-info/top_level.txt
greet_1-0.1.0.dist-info/RECORD
